FluentDNA/AnnotatedAlignment.py
FluentDNA/AnnotatedTrackLayout.py
FluentDNA/AnnotationAlignment.py
FluentDNA/Annotations.py
FluentDNA/ChainFiles.py
FluentDNA/ChainParser.py
FluentDNA/DefaultOrderedDict.py
FluentDNA/FluentDNAUtils.py
FluentDNA/HighlightedAnnotation.py
FluentDNA/Ideogram.py
FluentDNA/Layouts.py
FluentDNA/MultipleAlignmentLayout.py
FluentDNA/ParallelGenomeLayout.py
FluentDNA/RepeatAnnotations.py
FluentDNA/Span.py
FluentDNA/TileLayout.py
FluentDNA/TransposonLayout.py
FluentDNA/UniqueOnlyChainParser.py
FluentDNA/__init__.py
FluentDNA/deepzoom.py
FluentDNA/fluentdna.py
FluentDNA/image_resize_script.py
FluentDNA/use_lib.py
FluentDNA/example_data/British Ash Tree Genome.png
FluentDNA/example_data/Example 7 Gene Families from Fraxinus.png
FluentDNA/example_data/Gnetum montanum Annotation - blue gene - yellow exon - green CDS.png
FluentDNA/example_data/Gnetum_query_genes.gff
FluentDNA/example_data/Gnetum_sample_genes.gff
FluentDNA/example_data/Human selenoproteins.fa
FluentDNA/example_data/Human vs Chimpanzee_chr19.png
FluentDNA/example_data/gnetum_sample.fa
FluentDNA/example_data/hg38_chr19_sample.fa
FluentDNA/example_data/hg38_chr19_sample.png
FluentDNA/example_data/phiX.fa
FluentDNA/example_data/alignments/HOG10009.fa
FluentDNA/example_data/alignments/HOG11602.fa
FluentDNA/example_data/alignments/HOG15568.fa
FluentDNA/example_data/alignments/HOG21771.fa
FluentDNA/example_data/alignments/HOG3700.fa
FluentDNA/example_data/alignments/HOG3735.fa
FluentDNA/example_data/alignments/HOG9833.fa
FluentDNA/html_template/Biojs.Sequence.js
FluentDNA/html_template/Biojs.js
FluentDNA/html_template/DDV-license.txt
FluentDNA/html_template/LICENSE
FluentDNA/html_template/OpenSeadragon-license.txt
FluentDNA/html_template/README.txt
FluentDNA/html_template/biojs-apache-license.txt
FluentDNA/html_template/density.php
FluentDNA/html_template/fluentdna.css
FluentDNA/html_template/index.html
FluentDNA/html_template/jquery-1.7.min.js
FluentDNA/html_template/jquery-MIT-license.txt
FluentDNA-2.5.3.dist-info/METADATA
FluentDNA-2.5.3.dist-info/WHEEL
FluentDNA-2.5.3.dist-info/top_level.txt
FluentDNA-2.5.3.dist-info/RECORD
