Metadata-Version: 2.1
Name: FluentDNA
Version: 2.5.3
Summary: Visualization tool for bare fasta files.  Supports whole genome alignment and multiple sequence alignment.
Home-page: https://github.com/josiahseaman/FluentDNA
Author: Josiah Seaman, Bryan Hurst
Author-email: josiah@newline.us
License: UNKNOWN
Download-URL: https://github.com/josiahseaman/FluentDNA
Keywords: bioinformatics,dna,fasta,chain,alignment,species diversity
Platform: UNKNOWN
Classifier: Development Status :: 5 - Production/Stable
Classifier: Intended Audience :: Science/Research
Classifier: License :: OSI Approved :: Apache Software License
Classifier: Operating System :: OS Independent
Classifier: Programming Language :: Python
Classifier: Programming Language :: Python :: 3
Classifier: Programming Language :: Python :: 3.4
Classifier: Programming Language :: Python :: 3.5
Classifier: Programming Language :: Python :: 3.6
Classifier: Programming Language :: Python :: 3.7
Classifier: Topic :: Scientific/Engineering :: Bio-Informatics
Requires-Dist: Pillow (>=3.2.0)
Requires-Dist: psutil (>=5.4.5)
Requires-Dist: natsort (>=5.1.1)
Requires-Dist: numpy (>=1.13.3)
Requires-Dist: DNASkittleUtils (>=1.0.13)
Provides-Extra: optimized_alignment
Requires-Dist: blist (>=1.3.6) ; extra == 'optimized_alignment'
